slaviclean/__init__.py
slaviclean/config.py
slaviclean/profanity.py
slaviclean/profanity_dict_builder.py
slaviclean/sanitize_report.py
slaviclean/slavicleaner.py
slaviclean/preprocessor/__init__.py
slaviclean/preprocessor/deobfuscator.py
slaviclean/preprocessor/message_masker.py
slaviclean/preprocessor/morph_analyzer.py
slaviclean/preprocessor/patterns_loader.py
slaviclean/resources/__init__.py
slaviclean/resources/cyrillic_look_alike_map.csv
slaviclean/resources/latin_look_alike_map.csv
slaviclean/resources/profanity/__init__.py
slaviclean/resources/profanity/ru.csv
slaviclean/resources/profanity/uk.csv
slaviclean-0.1.0.dist-info/licenses/LICENSE
slaviclean-0.1.0.dist-info/METADATA
slaviclean-0.1.0.dist-info/WHEEL
slaviclean-0.1.0.dist-info/top_level.txt
slaviclean-0.1.0.dist-info/RECORD
