Metadata-Version: 2.4
Name: slaviclean
Version: 0.1.0
Summary: Text filter designed to cleanse text of profanity and offensive language, specifically tailored for Ukrainian, Russian, and Surzhik.
Author: Tetiana Lytvynenko
Author-email: lytvynenkotv@gmail.com
License: MIT
Keywords: nlp tools,natural language processing,text processing,linguistic tools,profanity filter,obscene filter,slavic languages,slavic profanity filter,slavic text cleaner,text sanitization
Classifier: Programming Language :: Python :: 3
Classifier: License :: OSI Approved :: MIT License
Classifier: Operating System :: OS Independent
Requires-Python: >=3.10
License-File: LICENSE
Requires-Dist: flexi_nlp_tools<0.7,>=0.6.0
Requires-Dist: pandas<2.3,>=2.2.3
Requires-Dist: spacy<3.9,>=3.8.4
Requires-Dist: pymorphy3<2.1,>=2.0
Requires-Dist: pymorphy3-dicts-uk<2.5,>=2.4
Dynamic: author
Dynamic: author-email
Dynamic: classifier
Dynamic: description
Dynamic: description-content-type
Dynamic: keywords
Dynamic: license
Dynamic: license-file
Dynamic: requires-dist
Dynamic: requires-python
Dynamic: summary
